robotframework_reportportal/__init__.py
robotframework_reportportal/exception.py
robotframework_reportportal/listener.py
robotframework_reportportal/logger.py
robotframework_reportportal/model.py
robotframework_reportportal/service.py
robotframework_reportportal/variables.py
robotframework_reportportal_eci-1.1.0.dist-info/LICENSE.txt
robotframework_reportportal_eci-1.1.0.dist-info/METADATA
robotframework_reportportal_eci-1.1.0.dist-info/WHEEL
robotframework_reportportal_eci-1.1.0.dist-info/top_level.txt
robotframework_reportportal_eci-1.1.0.dist-info/RECORD
